LICENSE
MANIFEST.in
README.md
requirements.txt
setup.py
raftos/__init__.py
raftos/conf.py
raftos/cryptor.py
raftos/exceptions.py
raftos/log.py
raftos/network.py
raftos/replicator.py
raftos/serializers.py
raftos/server.py
raftos/state.py
raftos/storage.py
raftos/timer.py
raftos.egg-info/PKG-INFO
raftos.egg-info/SOURCES.txt
raftos.egg-info/dependency_links.txt
raftos.egg-info/requires.txt
raftos.egg-info/top_level.txt