Metadata-Version: 1.0
Name: raftos
Version: 0.2.1
Summary: Raft replication in Python
Home-page: https://github.com/zhebrak/raftos
Author: Alexander Zhebrak
Author-email: fata2ex@gmail.com
License: MIT
Keywords: python,raft,replication
Platform: UNKNOWN
